odoo/addons/account_check_date/README.rst
odoo/addons/account_check_date/__init__.py
odoo/addons/account_check_date/__manifest__.py
odoo/addons/account_check_date/i18n/account_check_date.pot
odoo/addons/account_check_date/models/__init__.py
odoo/addons/account_check_date/models/account_payment.py
odoo/addons/account_check_date/readme/CONTRIBUTORS.rst
odoo/addons/account_check_date/readme/DESCRIPTION.rst
odoo/addons/account_check_date/readme/USAGE.rst
odoo/addons/account_check_date/static/description/icon.png
odoo/addons/account_check_date/static/description/index.html
odoo/addons/account_check_date/views/account_payment_views.xml
odoo13_addon_account_check_date-13.0.1.0.1.dev2.dist-info/METADATA
odoo13_addon_account_check_date-13.0.1.0.1.dev2.dist-info/WHEEL
odoo13_addon_account_check_date-13.0.1.0.1.dev2.dist-info/top_level.txt
odoo13_addon_account_check_date-13.0.1.0.1.dev2.dist-info/RECORD
